pwfluo/__init__.py
pwfluo/__main__.py
pwfluo/constants.py
pwfluo/icon.png
pwfluo/objects.py
pwfluo/wizards.py
pwfluo/protocols/__init__.py
pwfluo/protocols/protocol_base.py
pwfluo/protocols/protocol_import.py
pwfluo/protocols/import_/__init__.py
pwfluo/protocols/import_/base.py
pwfluo/tests/__init__.py
pwfluo/tests/test_fluo_base.py
scipion_fluo-0.1.0.dist-info/METADATA
scipion_fluo-0.1.0.dist-info/WHEEL
scipion_fluo-0.1.0.dist-info/entry_points.txt
scipion_fluo-0.1.0.dist-info/licenses/LICENSE
scipion_fluo-0.1.0.dist-info/RECORD
